{
	"Stock_Market_Prices_At_Timestamp": {
		"T1":{
			"Stock_1":69.32,
			"Stock_2":21.56,
			"Stock_3":21.12,
			"Stock_4":18.56,
			"Stock_5":20.67
		},
	
		"T2":{
			"Stock_1":74.34,
			"Stock_2":21.21,
			"Stock_3":18.01,
			"Stock_4":15.44,
			"Stock_5":14.67
		},

		"T3":{
			"Stock_1":17.11,
			"Stock_2":14.56,
			"Stock_3":23.80,
			"Stock_4":5.32,
			"Stock_5":54.66
		},

		"T4":{
			"Stock_1":6.21,
			"Stock_2":15.34,
			"Stock_3":21.67,
			"Stock_4":35.11,
			"Stock_5":49.76
		},

		"T5":{
			"Stock_1":13.11,
			"Stock_2":17.67,
			"Stock_3":22.12,
			"Stock_4":37.89,
			"Stock_5":44.23
		}
	}
}